[
    {
      "id": 1,
      "name": "Ordinateur portable",
      "description": "Un ordinateur portable fiable pour vos besoins quotidiens",
      "price": 499.99
    },
    {
      "id": 2,
      "name": "Casque audio",
      "description": "Un casque audio avec une qualité de son exceptionnelle",
      "price": 249.99
    },
    {
      "id": 3,
      "name": "Clavier sans fil",
      "description": "Un clavier sans fil pour une meilleure expérience utilisateur",
      "price": 29.99
    },
    {
      "id": 4,
      "name": "Souris bluetooth",
      "description": "Une souris bluetooth pour une meilleure expérience utilisateur",
      "price": 19.99
    },
    {
      "id": 5,
      "name": "Disque dur SSD",
      "description": "Un disque dur SSD de 512Go",
      "price": 149.99
    },
    {
      "id": 6,
      "name": "Tablette Samsung",
      "description": "Une tablette Samsung Galaxy Tab S6",
      "price": 399.99
    },
    {
      "id": 7,
      "name": "Chargeur Samsung",
      "description": "Un chargeur Samsung 45W",
      "price": 79.99
    },
    {
      "id": 8,
      "name": "Écouteurs Samsung",
      "description": "Des écouteurs Samsung Galaxy Buds+",
      "price": 129.99
    },
    {
      "id": 9,
      "name": "Écouteurs Apple",
      "description": "Des écouteurs Apple AirPods Pro",
      "price": 199.99
    },
    {
      "id": 10,
      "name": "Chargeur Apple",
      "description": "Un chargeur Apple 20W",
      "price": 29.99
    },
    {
      "id": 11,
      "name": "Tablette Apple",
      "description": "Une tablette Apple iPad Pro",
      "price": 899.99
    },
    {
      "id": 12,
      "name": "Ordinateur portable Apple",
      "description": "Un ordinateur portable Apple MacBook Pro",
      "price": 1499.99
    },
    {
      "id": 13,
      "name": "Clavier Apple",
      "description": "Un clavier Apple Magic Keyboard",
      "price": 99.99
    }
  ]
  